pose_transform/__init__.py
pose_transform/transform.py
pose_transform-0.3.0.dist-info/METADATA
pose_transform-0.3.0.dist-info/WHEEL
pose_transform-0.3.0.dist-info/top_level.txt
pose_transform-0.3.0.dist-info/RECORD
